MANIFEST.in
README.rst
setup.py
liquidluck/__init__.py
liquidluck/cli.py
liquidluck/filters.py
liquidluck/generator.py
liquidluck/options.py
liquidluck/utils.py
liquidluck.egg-info/PKG-INFO
liquidluck.egg-info/SOURCES.txt
liquidluck.egg-info/dependency_links.txt
liquidluck.egg-info/entry_points.txt
liquidluck.egg-info/requires.txt
liquidluck.egg-info/top_level.txt
liquidluck/_themes/default/README.md
liquidluck/_themes/default/theme.py
liquidluck/_themes/default/static/end.png
liquidluck/_themes/default/static/html5shiv.js
liquidluck/_themes/default/static/mobile.js
liquidluck/_themes/default/static/pygments.css
liquidluck/_themes/default/static/style.css
liquidluck/_themes/default/templates/404.html
liquidluck/_themes/default/templates/archive.html
liquidluck/_themes/default/templates/feed.xml
liquidluck/_themes/default/templates/layout.html
liquidluck/_themes/default/templates/page.html
liquidluck/_themes/default/templates/post.html
liquidluck/_themes/default/templates/tagcloud.html
liquidluck/readers/__init__.py
liquidluck/readers/base.py
liquidluck/readers/markdown.py
liquidluck/readers/restructuredtext.py
liquidluck/tools/__init__.py
liquidluck/tools/_settings.json
liquidluck/tools/_settings.py
liquidluck/tools/_settings.yml
liquidluck/tools/livereload.js
liquidluck/tools/server.py
liquidluck/tools/theme.py
liquidluck/tools/webhook.py
liquidluck/writers/__init__.py
liquidluck/writers/base.py
liquidluck/writers/contrib.py
liquidluck/writers/core.py
liquidluck/writers/extends.py