Metadata-Version: 1.0
Name: liquidluck
Version: 3.8.1
Summary: A lightweight static weblog generator
Home-page: http://lab.lepture.com/liquidluck/
Author: Hsiaoming Yang
Author-email: me@liquidluck.com
License: BSD License
Platform: UNKNOWN
Classifier: Development Status :: 4 - Beta
Classifier: Environment :: Console
Classifier: License :: OSI Approved :: BSD License
Classifier: Operating System :: MacOS
Classifier: Operating System :: POSIX
Classifier: Operating System :: POSIX :: Linux
Classifier: Programming Language :: Python
Classifier: Programming Language :: Python :: 2.6
Classifier: Programming Language :: Python :: 2.7
Classifier: Programming Language :: Python :: 3.1
Classifier: Programming Language :: Python :: 3.2
Classifier: Programming Language :: Python :: Implementation :: CPython
Classifier: Topic :: Text Processing :: Markup
